pyspatialml/__init__.py
pyspatialml/_extraction.py
pyspatialml/_plotting.py
pyspatialml/_prediction.py
pyspatialml/_rasterbase.py
pyspatialml/datasets/__init__.py
pyspatialml/datasets/chnl_dist.tif
pyspatialml/datasets/dem.tif
pyspatialml/datasets/dist.tif
pyspatialml/datasets/extracted_pixels.txt
pyspatialml/datasets/ffreq.tif
pyspatialml/datasets/landimg2.tif
pyspatialml/datasets/landimg3.tif
pyspatialml/datasets/landimg4.tif
pyspatialml/datasets/landsat96_labelled_pixels.tif
pyspatialml/datasets/landsat96_points.dbf
pyspatialml/datasets/landsat96_points.prj
pyspatialml/datasets/landsat96_points.shp
pyspatialml/datasets/landsat96_points.shx
pyspatialml/datasets/landsat96_polygons.dbf
pyspatialml/datasets/landsat96_polygons.prj
pyspatialml/datasets/landsat96_polygons.shp
pyspatialml/datasets/landsat96_polygons.shx
pyspatialml/datasets/landsat_multiband.tif
pyspatialml/datasets/lsat7_2000_10.tif
pyspatialml/datasets/lsat7_2000_20.tif
pyspatialml/datasets/lsat7_2000_30.tif
pyspatialml/datasets/lsat7_2000_40.tif
pyspatialml/datasets/lsat7_2000_50.tif
pyspatialml/datasets/lsat7_2000_70.tif
pyspatialml/datasets/meuse.dbf
pyspatialml/datasets/meuse.prj
pyspatialml/datasets/meuse.py
pyspatialml/datasets/meuse.shp
pyspatialml/datasets/meuse.shx
pyspatialml/datasets/mrvbf.tif
pyspatialml/datasets/nc.py
pyspatialml/datasets/rsp.tif
pyspatialml/datasets/slope.tif
pyspatialml/datasets/soil.tif
pyspatialml/datasets/strata.tif
pyspatialml/datasets/twi.tif
pyspatialml/locindexer.py
pyspatialml/preprocessing.py
pyspatialml/raster.py
pyspatialml/rasterlayer.py
pyspatialml/rasterstats.py
pyspatialml/transformers.py
pyspatialml/vector.py
pyspatialml-0.22.1.dist-info/LICENSE
pyspatialml-0.22.1.dist-info/METADATA
pyspatialml-0.22.1.dist-info/WHEEL
pyspatialml-0.22.1.dist-info/RECORD
