Metadata-Version: 2.1
Name: pyspatialml
Version: 0.22.1
Summary: Machine learning classification and regression modelling for spatial raster data.
Home-page: https://stevenpawley.github.io/Pyspatialml/
License: GPL-3.0-or-later
Author: Steven Pawley
Author-email: dr.stevenpawley@gmail.com
Requires-Python: >=3.9,<4.0
Classifier: License :: OSI Approved :: GNU General Public License v3 or later (GPLv3+)
Classifier: Programming Language :: Python :: 3
Classifier: Programming Language :: Python :: 3.9
Classifier: Programming Language :: Python :: 3.10
Classifier: Programming Language :: Python :: 3.11
Classifier: Programming Language :: Python :: 3.12
Requires-Dist: affine (>=2.4.0,<3.0.0)
Requires-Dist: geopandas (>=0.14.4,<0.15.0)
Requires-Dist: matplotlib (>=3.9.0,<4.0.0)
Requires-Dist: numpy (>=1.26.4,<2.0.0)
Requires-Dist: pandas (>=2.2.2,<3.0.0)
Requires-Dist: rasterio (>=1.3.10,<2.0.0)
Requires-Dist: scikit-learn (>=1.4.2,<2.0.0)
Requires-Dist: scipy (>=1.13.0,<2.0.0)
Requires-Dist: shapely (>=2.0.4,<3.0.0)
Requires-Dist: tqdm (>=4.66.4,<5.0.0)
Project-URL: Repository, https://github.com/stevenpawley/Pyspatialml
